mdhtmlgen/__init__.py
mdhtmlgen/__main__.py
mdhtmlgen/main.py
mdhtmlgen-0.8.dist-info/LICENSE.txt
mdhtmlgen-0.8.dist-info/METADATA
mdhtmlgen-0.8.dist-info/WHEEL
mdhtmlgen-0.8.dist-info/top_level.txt
mdhtmlgen-0.8.dist-info/RECORD
